dagex-2026.17.dist-info/METADATA
dagex-2026.17.dist-info/WHEEL
dagex/__init__.py
dagex/dagex.cp312-win_amd64.pyd
dagex-2026.17.dist-info/RECORD
