Metadata-Version: 2.1
Name: dagex
Version: 2026.17
Summary: A pure Rust DAG executor supporting implicit node connections, branching, and config sweeps
Keywords: dag,graph,execution,pipeline,workflow
Home-Page: https://github.com/briday1/dagex
Author: briday1 <your-email@example.com>
Author-email: briday1 <your-email@example.com>
License: MIT
Requires-Python: >=3.8
Project-URL: Source Code, https://github.com/briday1/dagex
